README.txt
setup.py
PyBitly.egg-info/PKG-INFO
PyBitly.egg-info/SOURCES.txt
PyBitly.egg-info/dependency_links.txt
PyBitly.egg-info/requires.txt
PyBitly.egg-info/top_level.txt
pybitly/__init__.py
pybitly/api.py
pybitly/test/__init__.py