Metadata-Version: 1.0
Name: PyBitly
Version: 0.1.0
Summary: Great wrapper for bit.ly
Home-page: http://pypi.python.org/pypi/PyBitly/
Author: Marcin Lipiec
Author-email: marcin.lipiec@yamatai.pl
License: LICENSE.txt
Platform: UNKNOWN
